{
  "seoul_tma": {
    "id": "t01_seoul",
    "name": "Seoul TMA",
    "vertical_limits": "FL185 / 1000ft AGL",
    "coordinates": [
      [126.1647, 37.6528], [126.6811, 37.7194], [126.8811, 37.6361],
      [127.6644, 37.9694], [127.6644, 37.2719], [127.3978, 37.2528],
      [127.3144, 37.3028], [127.1478, 37.3028], [126.9644, 37.3528],
      [126.8061, 37.3403], [126.6103, 37.1486], [126.5286, 37.1397],
      [126.3661, 37.0994], [125.8025, 37.0881], [125.7981, 37.2694],
      [125.5481, 37.3528], [126.1647, 37.6528]
    ]
  },
  "restricted_zones": [
    {
      "id": "P73",
      "name": "RK P73 (국회의사당)",
      "type": "P",
      "color": "#ff0000",
      "boundary": [[126.977222, 37.535833], [126.995278, 37.535833], [126.995278, 37.542222], [126.977222, 37.542222], [126.977222, 37.535833]]
    },
    {
      "id": "R75",
      "name": "RK R75 (서울 도심)",
      "type": "R",
      "color": "#ff4444",
      "boundary": [
        [126.806667, 37.663611], [126.803611, 37.631111], [126.798333, 37.616944],
        [126.804722, 37.591667], [126.806667, 37.569167], [126.956111, 37.448056],
        [127.060556, 37.448056], [127.113056, 37.5425], [127.158333, 37.579722],
        [127.141667, 37.615556], [127.133333, 37.640833], [127.086944, 37.675833],
        [127.054722, 37.693333], [127.027778, 37.7], [126.883056, 37.632778],
        [126.806667, 37.663611]
      ]
    }
  ],
  "danger_zones": [
    {"id": "D20", "name": "RK D20", "center": [127.096389, 37.535556], "radius_nm": 0.2},
    {"id": "D21", "name": "RK D21", "center": [127.072778, 37.5375], "radius_nm": 0.3},
    {"id": "D25", "name": "RK D25", "center": [127.016667, 37.483333], "radius_nm": 0.3},
    {"id": "D26", "name": "RK D26", "center": [126.924444, 37.491111], "radius_nm": 0.3},
    {"id": "D28", "name": "RK D28", "center": [126.890833, 37.508056], "radius_nm": 0.3},
    {"id": "D30", "name": "RK D30", "center": [126.874444, 37.527222], "radius_nm": 0.4}
  ],
  "ctr_zones": [
    {"id": "gimpo_ctr", "name": "Gimpo CTR", "center": [126.791, 37.558], "radius_nm": 5, "ceiling_ft": 2500, "color": "#2ECC71"},
    {"id": "incheon_ctr", "name": "Incheon CTR", "center": [126.451, 37.469], "radius_nm": 5, "ceiling_ft": 3000, "color": "#3498DB"}
  ],
  "uam_corridors": [
    {
      "id": "yeouido_jamsil",
      "name": "여의도 → 잠실 UAM 회랑",
      "color": "#f97316",
      "waypoints": [
        {"name": "여의도 버티포트", "lat": 37.5219, "lon": 126.9245, "alt": 300},
        {"name": "용산 경유", "lat": 37.5350, "lon": 126.9700, "alt": 300},
        {"name": "한남대교", "lat": 37.5280, "lon": 127.0000, "alt": 300},
        {"name": "압구정 경유", "lat": 37.5260, "lon": 127.0280, "alt": 300},
        {"name": "잠실대교", "lat": 37.5190, "lon": 127.0800, "alt": 300},
        {"name": "잠실 버티포트", "lat": 37.5133, "lon": 127.1001, "alt": 300}
      ]
    }
  ],
  "airports": [
    {"id": "RKSS", "name": "김포국제공항", "coords": [126.7975, 37.556944]},
    {"id": "RKSM", "name": "서울공항(성남)", "coords": [127.114167, 37.445833]},
    {"id": "RKSI", "name": "인천국제공항", "coords": [126.439167, 37.4625]}
  ]
}
